algosec/__init__.py
algosec/errors.py
algosec/flow_comparison_logic.py
algosec/helpers.py
algosec/models.py
algosec/api_clients/__init__.py
algosec/api_clients/base.py
algosec/api_clients/business_flow.py
algosec/api_clients/fire_flow.py
algosec/api_clients/firewall_analyzer.py
algosec/examples/__init__.py
algosec/examples/create_application_flow_in_abf.py
algosec/examples/create_change_request_in_aff.py
algosec/examples/get_application_flows_from_abf.py
algosec-1.3.5.dist-info/LICENSE
algosec-1.3.5.dist-info/METADATA
algosec-1.3.5.dist-info/WHEEL
algosec-1.3.5.dist-info/top_level.txt
algosec-1.3.5.dist-info/RECORD
