Metadata-Version: 2.1
Name: algosec
Version: 1.3.5
Summary: The AlgoSec SDK for Python
Home-page: https://github.com/algosec/algosec-python
Author: Almog Cohen
Author-email: support@algosec.com
License: MIT
Keywords: algosec businessflow fireflow firewallanalyzer security policy management network security
Platform: UNKNOWN
Classifier: Intended Audience :: Developers
Classifier: Intended Audience :: Information Technology
Classifier: License :: OSI Approved :: MIT License
Classifier: Natural Language :: English
Classifier: Topic :: Software Development :: Libraries :: Python Modules
Classifier: Programming Language :: Python :: Implementation :: CPython
Classifier: Programming Language :: Python :: Implementation :: PyPy
Classifier: Programming Language :: Python :: 2
Classifier: Programming Language :: Python :: 2.7
Classifier: Programming Language :: Python :: 3
Classifier: Programming Language :: Python :: 3.4
Classifier: Programming Language :: Python :: 3.5
Classifier: Programming Language :: Python :: 3.6
Classifier: Programming Language :: Python :: 3.7
Requires-Python: >=2.7, !=3.0.*, !=3.1.*, !=3.2.*, !=3.3.*
Requires-Dist: requests
Requires-Dist: suds-jurko (>=0.6)
Requires-Dist: suds-requests (>=0.4.0)
Requires-Dist: ipaddress
Requires-Dist: six
Requires-Dist: deprecated
